CHANGELOG.md
MANIFEST.in
README.md
setup.cfg
setup.py
versioneer.py
src/libreflow/__init__.py
src/libreflow.extensions.anpo.mark_img_sequence.egg-info/PKG-INFO
src/libreflow.extensions.anpo.mark_img_sequence.egg-info/SOURCES.txt
src/libreflow.extensions.anpo.mark_img_sequence.egg-info/dependency_links.txt
src/libreflow.extensions.anpo.mark_img_sequence.egg-info/top_level.txt
src/libreflow/extensions/__init__.py
src/libreflow/extensions/anpo/__init__.py
src/libreflow/extensions/anpo/mark_img_sequence/__init__.py
src/libreflow/extensions/anpo/mark_img_sequence/_version.py